[
    {
        "name": "Builders Club",
        "logo": "images/sponsors/buildersclub.webp"
    },
    {
        "name": "Den 1880",
        "logo": "images/sponsors/denlogo.png"
    },
    {
        "name": "Dreamside Digital",
        "logo": "images/sponsors/dreamsidelogo.png"
    },
    {
        "name": "Foxxwood",
        "logo": "images/sponsors/foxxwoodlogo.png"
    },
    {
        "name": "SmartWR",
        "logo": "images/sponsors/swrllogo.png"
    },
    {
        "name": "Tiny Home Takeout",
        "logo": "images/sponsors/tinyhometakeout.png"
    }
]
